cellmaps_sdk/__init__.py
cellmaps_sdk/__main__.py
cellmaps_sdk/_cli_utils.py
cellmaps_sdk/_config.py
cellmaps_sdk/_test_utils.py
cellmaps_sdk/_utils.py
cellmaps_sdk/data.py
cellmaps_sdk/data_utils.py
cellmaps_sdk/process.py
cellmaps_sdk/py.typed
cellmaps_sdk-0.1.0.dist-info/LICENSE.txt
cellmaps_sdk-0.1.0.dist-info/METADATA
cellmaps_sdk-0.1.0.dist-info/WHEEL
cellmaps_sdk-0.1.0.dist-info/entry_points.txt
cellmaps_sdk-0.1.0.dist-info/top_level.txt
cellmaps_sdk-0.1.0.dist-info/RECORD
